sportsreference/__init__.py
sportsreference/constants.py
sportsreference/decorators.py
sportsreference/utils.py
sportsreference/fb/__init__.py
sportsreference/fb/constants.py
sportsreference/fb/fb_utils.py
sportsreference/fb/roster.py
sportsreference/fb/schedule.py
sportsreference/fb/squad_ids.py
sportsreference/fb/team.py
sportsreference/mlb/__init__.py
sportsreference/mlb/boxscore.py
sportsreference/mlb/constants.py
sportsreference/mlb/player.py
sportsreference/mlb/roster.py
sportsreference/mlb/schedule.py
sportsreference/mlb/teams.py
sportsreference/nba/__init__.py
sportsreference/nba/boxscore.py
sportsreference/nba/constants.py
sportsreference/nba/player.py
sportsreference/nba/roster.py
sportsreference/nba/schedule.py
sportsreference/nba/teams.py
sportsreference/ncaab/__init__.py
sportsreference/ncaab/boxscore.py
sportsreference/ncaab/conferences.py
sportsreference/ncaab/constants.py
sportsreference/ncaab/player.py
sportsreference/ncaab/rankings.py
sportsreference/ncaab/roster.py
sportsreference/ncaab/schedule.py
sportsreference/ncaab/teams.py
sportsreference/ncaaf/__init__.py
sportsreference/ncaaf/boxscore.py
sportsreference/ncaaf/conferences.py
sportsreference/ncaaf/constants.py
sportsreference/ncaaf/player.py
sportsreference/ncaaf/rankings.py
sportsreference/ncaaf/roster.py
sportsreference/ncaaf/schedule.py
sportsreference/ncaaf/teams.py
sportsreference/nfl/__init__.py
sportsreference/nfl/boxscore.py
sportsreference/nfl/constants.py
sportsreference/nfl/player.py
sportsreference/nfl/roster.py
sportsreference/nfl/schedule.py
sportsreference/nfl/teams.py
sportsreference/nhl/__init__.py
sportsreference/nhl/boxscore.py
sportsreference/nhl/constants.py
sportsreference/nhl/player.py
sportsreference/nhl/roster.py
sportsreference/nhl/schedule.py
sportsreference/nhl/teams.py
tests/__init__.py
tests/exhaustive/__init__.py
tests/exhaustive/fb_tests.py
tests/exhaustive/mlb_tests.py
tests/exhaustive/nba_tests.py
tests/exhaustive/ncaab_tests.py
sportsreference-0.5.2.dist-info/LICENSE
sportsreference-0.5.2.dist-info/METADATA
sportsreference-0.5.2.dist-info/WHEEL
sportsreference-0.5.2.dist-info/top_level.txt
sportsreference-0.5.2.dist-info/RECORD
