Metadata-Version: 1.2
Name: sportsreference
Version: 0.5.2
Summary: A free sports API written for python
Home-page: https://github.com/roclark/sportsreference
Author: Robert Clark
Author-email: robdclark@outlook.com
License: MIT
Keywords: stats sports api sportsreference machine learning
Platform: UNKNOWN
Classifier: Programming Language :: Python :: 3.5
Classifier: Programming Language :: Python :: 3.6
Classifier: Programming Language :: Python :: 3.7
Classifier: Programming Language :: Python :: 3.8
Classifier: License :: OSI Approved :: MIT License
Classifier: Operating System :: POSIX :: Linux
Requires-Python: >=3.5
